wallverse/com.wallverse.app.plist
wallverse/database.py
wallverse/font_manager.py
wallverse/font_preview_window.py
wallverse/home_tab.py
wallverse/main.py
wallverse/preferences_tab.py
wallverse/quote_manager.py
wallverse/quotes_tab.py
wallverse/settings.json
wallverse/settings_manager.py
wallverse/style_tab.py
wallverse/wallpaper.py
wallverse/wallverse-startup.vbs
wallverse/ui_resources/custom.txt
wallverse/ui_resources/dark-mode-logo.png
wallverse/ui_resources/icon-linux.png
wallverse/ui_resources/icon.ico
wallverse/ui_resources/light-mode-logo.png
wallverse/ui_resources/transparent.ico
wallverse/ui_resources/background_images/dark-bg.jpg
wallverse/ui_resources/background_images/light-bg.jpg
wallverse/ui_resources/background_images/petr-sidorov-GESOWH4YLRI-unsplash.jpg
wallverse/ui_resources/fonts/NotoSans-Regular.ttf
wallverse-0.1.0.dist-info/LICENSE
wallverse-0.1.0.dist-info/METADATA
wallverse-0.1.0.dist-info/WHEEL
wallverse-0.1.0.dist-info/entry_points.txt
wallverse-0.1.0.dist-info/top_level.txt
wallverse-0.1.0.dist-info/RECORD
