Metadata-Version: 2.1
Name: wallverse
Version: 0.1.0
Summary: Random Topic Based Quotations as Your Wallpaper
Home-page: https://github.com/aref-dev/WallVerse
Author: Aref Nasrollah Zadeh
Author-email: aref.anz@outlook.com
License: MIT
Keywords: wallpaper,quotes,multiplatform,desktop customization,motivational,wisdom,funny
Classifier: Development Status :: 3 - Alpha
Classifier: Environment :: MacOS X
Classifier: Environment :: Win32 (MS Windows)
Classifier: Environment :: X11 Applications
Classifier: Intended Audience :: End Users/Desktop
Classifier: License :: OSI Approved :: MIT License
Classifier: Operating System :: MacOS
Classifier: Operating System :: Microsoft :: Windows
Classifier: Operating System :: POSIX :: Linux
Classifier: Programming Language :: Python :: 3.10
Classifier: Topic :: Desktop Environment
Classifier: Topic :: Utilities
Requires-Python: >=3.10
License-File: LICENSE
Requires-Dist: arabic-reshaper ==3.0.0
Requires-Dist: cowsay ==6.1
Requires-Dist: CTkColorPicker ==0.8.0
Requires-Dist: customtkinter ==5.2.1
Requires-Dist: darkdetect ==0.8.0
Requires-Dist: packaging ==23.2
Requires-Dist: Pillow ==10.1.0
Requires-Dist: pystray ==0.19.5
Requires-Dist: python-bidi ==0.4.2
Requires-Dist: screeninfo ==0.8.1
Requires-Dist: fonttools ==4.45.1
Requires-Dist: pypiwin32 ==223 ; platform_system == "Windows"
Requires-Dist: winshell ==0.6 ; platform_system == "Windows"
